shipyard_sqlserver/__init__.py
shipyard_sqlserver/cli/__init__.py
shipyard_sqlserver/cli/authtest.py
shipyard_sqlserver/cli/execute_sql.py
shipyard_sqlserver/cli/store_query_results.py
shipyard_sqlserver/cli/upload_file.py
shipyard_sqlserver/exceptions.py
shipyard_sqlserver/sqlserver.py
shipyard_sqlserver-0.2.1.dist-info/METADATA
shipyard_sqlserver-0.2.1.dist-info/WHEEL
shipyard_sqlserver-0.2.1.dist-info/RECORD
