Metadata-Version: 2.1
Name: shipyard-sqlserver
Version: 0.2.1
Summary: A local client for connecting and working with Sql Server Databases
License: Apache 2.0
Author: wrp801
Author-email: wespoulsen@gmail.com
Requires-Python: >=3.9,<4.0
Classifier: License :: Other/Proprietary License
Classifier: Programming Language :: Python :: 3
Classifier: Programming Language :: Python :: 3.9
Classifier: Programming Language :: Python :: 3.10
Classifier: Programming Language :: Python :: 3.11
Requires-Dist: pandas (>=2.0,<3.0)
Requires-Dist: pyodbc (>=5.0.1,<6.0.0)
Requires-Dist: shipyard-bp-utils (==1.2.0)
Requires-Dist: shipyard-templates (==0.8.0)
Requires-Dist: sqlalchemy (>=2.0.28,<3.0.0)
